odoo/addons/stock_release_channel_plan_depot/README.rst
odoo/addons/stock_release_channel_plan_depot/__init__.py
odoo/addons/stock_release_channel_plan_depot/__manifest__.py
odoo/addons/stock_release_channel_plan_depot/i18n/fr.po
odoo/addons/stock_release_channel_plan_depot/i18n/it.po
odoo/addons/stock_release_channel_plan_depot/i18n/stock_release_channel_plan_depot.pot
odoo/addons/stock_release_channel_plan_depot/models/__init__.py
odoo/addons/stock_release_channel_plan_depot/models/stock_release_channel_preparation_plan.py
odoo/addons/stock_release_channel_plan_depot/readme/CONTRIBUTORS.rst
odoo/addons/stock_release_channel_plan_depot/readme/DESCRIPTION.rst
odoo/addons/stock_release_channel_plan_depot/static/description/icon.png
odoo/addons/stock_release_channel_plan_depot/static/description/index.html
odoo/addons/stock_release_channel_plan_depot/views/stock_release_channel_preparation_plan.xml
odoo_addon_stock_release_channel_plan_depot-16.0.1.0.0.4.dist-info/METADATA
odoo_addon_stock_release_channel_plan_depot-16.0.1.0.0.4.dist-info/WHEEL
odoo_addon_stock_release_channel_plan_depot-16.0.1.0.0.4.dist-info/top_level.txt
odoo_addon_stock_release_channel_plan_depot-16.0.1.0.0.4.dist-info/RECORD
