Metadata-Version: 2.1
Name: odoo-addon-stock_release_channel_plan_depot
Version: 16.0.1.0.0.4
Summary: This module allows users to set partner depot on stock release channel preparation plan.
Home-page: https://github.com/OCA/wms
Author: Camptocamp, Odoo Community Association (OCA)
Author-email: support@odoo-community.org
License: AGPL-3
Classifier: Programming Language :: Python
Classifier: Framework :: Odoo
Classifier: Framework :: Odoo :: 16.0
Classifier: License :: OSI Approved :: GNU Affero General Public License v3
Requires-Python: >=3.10
Requires-Dist: odoo-addon-stock-depot<16.1dev,>=16.0dev
Requires-Dist: odoo-addon-stock-release-channel-plan<16.1dev,>=16.0dev
Requires-Dist: odoo<16.1dev,>=16.0a
